<?xml version="1.0" encoding="UTF-8"?>
<objects serializationModel="Studio.02.00.00">
	<object class="AudioFile" id="{28f722f2-d4c5-47cd-be75-7da6a8c157b9}">
		<property name="assetPath">
			<value>sfx/click_2.wav</value>
		</property>
		<property name="frequencyInKHz">
			<value>48</value>
		</property>
		<property name="channelCount">
			<value>2</value>
		</property>
		<property name="length">
			<value>2.5288541666666666</value>
		</property>
		<relationship name="masterAssetFolder">
			<destination>{57e360c1-91e9-4342-80bf-ec1474b95eb0}</destination>
		</relationship>
	</object>
</objects>
